README.md
setup.py
CAE_Jake_HP_145.egg-info/PKG-INFO
CAE_Jake_HP_145.egg-info/SOURCES.txt
CAE_Jake_HP_145.egg-info/dependency_links.txt
CAE_Jake_HP_145.egg-info/top_level.txt
functioncae/__init__.py
functioncae/cae_cnn_models.py
functioncae/caehelper.py
functioncae/classes_cae.py