Metadata-Version: 2.1
Name: CAE-Jake-HP-145
Version: 1.4.4
Summary: CAE helper functions, models and classes
Home-page: https://github.com/Jake145/CAE-for-DM-segmentation
Author: Jake Harold Pensavalle
Author-email: jakeharold.pensavalle@gmail.com
License: UNKNOWN
Platform: UNKNOWN
Classifier: Programming Language :: Python :: 3
Classifier: Operating System :: OS Independent
Requires-Python: >=3.0
